{
  "type": "blockhut_logs",
  "textures": [
    {
      "name": "texture_wood",
      "url": "./assets/textures/wood/texture_wood.jpg"
    },
    {
      "name": "texture_wood_light",
      "url": "./assets/textures/wood/wood_texture_light.png"
    },
    {
      "name": "texture_wood_normal",
      "url": "./assets/textures/wood/wood_texture_normal.png"
    },
    {
      "name": "texture_wood_roughness",
      "url": "./assets/textures/wood/wood_texture_roughness.png"
    }
  ],
  "models": [
    {
      "name": "kosour",
      "url": "./assets/models/kosour.obj"
    },
    {
      "name": "log_50x50",
      "url": "./assets/models/wall/log_50x50.obj"
    }
  ],
  "materials": [
    {
      "name": "material_wood",
      "type": "standart",
      "map": "texture_wood",
      "normalMap": "texture_wood_normal",
      "metalness": 0
    },
    {
      "name": "material_wood_light",
      "type": "standart",
      "map": "texture_wood_light",
      "normalMap": "texture_wood_normal",
      "roughness": 1,
      "roughnessMap": "texture_wood_roughness",
      "metalness": 0
    }
  ],
  "objects": [
    {
      "name": "log_lf",
      "model": "log_50x50",
      "material": "material_wood_light"
    },
    {
      "name": "log_lb",
      "model": "log_50x50",
      "material": "material_wood_light"
    },
    {
      "name": "log_rf",
      "model": "log_50x50",
      "material": "material_wood_light"
    },
    {
      "name": "log_rb",
      "model": "log_50x50",
      "material": "material_wood_light"
    },
    {
      "name": "kosour_l",
      "model": "kosour",
      "material": "material_wood",
      "rotation": {
        "x": 0,
        "y": 90,
        "z": 0
      }
    },
    {
      "name": "kosour_r",
      "model": "kosour",
      "material": "material_wood",
      "rotation": {
        "x": 0,
        "y": 90,
        "z": 0
      },
      "scale": {
        "x": 1,
        "y": 1,
        "z": -1
      }
    }
  ],
  "parts": [
    {
      "object": "log_lf",
      "scaling": true,
      "initial": {
        "x": 0,
        "y": 1000,
        "z": 0
      },
      "relative": {
        "x": {
          "a": 0,
          "b": 0
        },
        "z": {
          "a": 0.5,
          "b": 0
        }
      }
    },
    {
      "object": "log_lb",
      "scaling": true,
      "initial": {
        "x": 0,
        "y": 1000,
        "z": 0
      },
      "relative": {
        "x": {
          "a": 0,
          "b": 0
        },
        "z": {
          "a": 0.5,
          "b": -75
        }
      }
    },
    {
      "object": "log_rf",
      "scaling": true,
      "initial": {
        "x": 0,
        "y": 1000,
        "z": 0
      },
      "relative": {
        "x": {
          "a": 1,
          "b": -50
        },
        "z": {
          "a": 0.5,
          "b": 0
        }
      }
    },
    {
      "object": "log_rb",
      "scaling": true,
      "initial": {
        "x": 0,
        "y": 1000,
        "z": 0
      },
      "relative": {
        "x": {
          "a": 1,
          "b": -50
        },
        "z": {
          "a": 0.5,
          "b": -75
        }
      }
    },
    {
      "object": "kosour_l",
      "relative": {
        "x": {
          "a": 0,
          "b": 50
        },
        "y": {
          "a": 1,
          "b": 0
        },
        "z": {
          "a": 0.5,
          "b": 0
        }
      }
    },
    {
      "object": "kosour_r",
      "relative": {
        "x": {
          "a": 1,
          "b": -50
        },
        "y": {
          "a": 1,
          "b": 0
        },
        "z": {
          "a": 0.5,
          "b": 0
        }
      }
    }
  ],
  "customizations": []
}