{
  "textures": [],
  "models": [
    {
      "name": "glass_window_1m_glass",
      "url": "./assets/models/glass_window/window_glass_1.obj"
    }
  ],
  "materials": [
    {
      "name": "glass_window_glass",
      "type": "standart",
      "color": "#ffffff",
      "metalness": 0.1,
      "roughness": 0.1,
      "opacity": 0.2,
      "transparent": true
    }
  ],
  "objects": [
    {
      "name": "glass_window_glass",
      "model": "glass_window_1m_glass",
      "material": "glass_window_glass",
      "scale": {
        "x": 0.01,
        "y": 0.01,
        "z": 0.01
      }
    }
  ],
  "type": "glass_1m_glass",
  "parts": [
    {
      "object": "glass_window_glass",
      "scaling": true,
      "initial": {
        "x": 1000,
        "y": 2200,
        "z": 0
      }
    }
  ]
}